
[
    {
        "title": "Understanding climate-water-energy-food nexus and streamlining water-related policies",
        "purpose": "Building a low-carbon, climate resilient future (LC).",
        "documents_submission_date_start": "2020-09-15",
        "documents_submission_date_end": "2020-09-12",
        "documents_submission_time_end": "18:46",
        "is_urgent": true,
        "competition_results_date": "2020-08-20",
        "fund_name": "Horizon 2020",
        "country": "USA",
        "allowed_participant_countries": "Ukraine,Poland",
        "id": "123213fdsfsdf",
        "field_of_knoweledge": "Climate",
        "specific_objectives": "The objective of this action is to develop and test innovative solutions, improved operations and integrated management and planning for achieving water, energy and food security and safety within the planetary boundaries and resolve conflicts",
        "expected_impact": "long term",
        "description": "this grant is very important for our society. It brings new ideas to the Programming world.",
        "allowed_participants": "universities, academy",
        "allowed_participants_age": 18,
        "program_budget": 23000,
        "project_budget": "up to 50 t. EUR",
        "type": "individual",
        "is_scientific_degree_required": true,
        "minimal_scientist_experience": "greater than 5 years",
        "link": "https://erasmusplus.org.ua/erasmus/pro-prohramu.html"
    },
    {
        "title": "Bilology",
        "purpose": "Giving up; to surrender..",
        "documents_submission_date_start": "2021-05-11",
        "documents_submission_date_end": "2021-05-11",
        "documents_submission_time_end": "12:11",
        "is_urgent": true,
        "competition_results_date": "2021-11-01",
        "fund_name": "Horizon 2020",
        "country": "Canada",
        "allowed_participant_countries": "Canada",
        "id": "fdsfsf1f2v",
        "field_of_knoweledge": "Bilology",
        "specific_objectives": "researching of nanocomposit materials in biology",
        "expected_impact": "short term",
        "description": "this grant is very important for our society. It brings new ideas to the Programming world.",
        "allowed_participants": "small bussiness, academy",
        "allowed_participants_age": 50,
        "program_budget": 310000000,
        "project_budget": "from 20 t. to 50 t. EUR",
        "type": "collectibe",
        "is_scientific_degree_required": false,
        "minimal_scientist_experience": "less than 1 year",
        "link": "https://en.wikipedia.org/wiki/Fuzzy_logic"
    },
    {
        "title": "Medicine",
        "purpose": "Something that occurs too early before preparations are ready. Starting too soon.",
        "documents_submission_date_start": "2019-01-12",
        "documents_submission_date_end": "2019-01-15",
        "documents_submission_time_end": "14:21",
        "is_urgent": false,
        "competition_results_date": "2019-02-01",
        "fund_name": "NAWA",
        "country": "China",
        "allowed_participant_countries": "Canada",
        "id": "231sfds",
        "field_of_knoweledge": "Medicine",
        "specific_objectives": "researching of therapy impotrant things",
        "expected_impact": "short term",
        "description": "this grant is very important for our society. It brings new ideas to the Programming world.",
        "allowed_participants": "small bussiness, academy",
        "allowed_participants_age": 50,
        "program_budget": 310000000,
        "project_budget": "from 20 t. to 50 t. EUR",
        "type": "collectibe",
        "is_scientific_degree_required": false,
        "minimal_scientist_experience": "less than 1 year",
        "link": "https://www.tandfonline.com/doi/full/10.1080/24751839.2017.1364040"
    },
    {
        "title": "Machine Learnining",
        "purpose": "A feeling that something is not quite right, or awry.",
        "documents_submission_date_start": "2019-01-12",
        "documents_submission_date_end": "2019-01-15",
        "documents_submission_time_end": "14:21",
        "is_urgent": false,
        "competition_results_date": "2019-02-01",
        "fund_name": "NAWA",
        "country": "China",
        "allowed_participant_countries": "Canada",
        "id": "231sfds",
        "field_of_knoweledge": "Machine Learning",
        "specific_objectives": "researching of machine learnign technology",
        "expected_impact": "short term",
        "description": "this grant is very important for our society. It brings new ideas to the Programming world.",
        "allowed_participants": "small bussiness, academy",
        "allowed_participants_age": 50,
        "program_budget": 310000000,
        "project_budget": "from 20 t. to 50 t. EUR",
        "type": "collectibe",
        "is_scientific_degree_required": true,
        "minimal_scientist_experience": "less than 1 year",
        "link": "https://content.iospress.com/articles/journal-of-intelligent-and-fuzzy-systems/ifs169843"
    },
    {
        "title": "Machine learning 1",
        "purpose": "One who may seem plain at first in appearance or capability, but later turns out to be beautiful or great.",
        "documents_submission_date_start": "2019-01-12",
        "documents_submission_date_end": "2019-01-15",
        "documents_submission_time_end": "14:21",
        "is_urgent": false,
        "competition_results_date": "2019-02-01",
        "fund_name": "NAWA",
        "country": "China",
        "allowed_participant_countries": "Canada",
        "id": "231sfds",
        "field_of_knoweledge": "Machine Learning",
        "specific_objectives": "researching of machine learnign technology",
        "expected_impact": "short term",
        "description": "this grant is very important for our society. It brings new ideas to the Programming world.",
        "allowed_participants": "small bussiness, academy",
        "allowed_participants_age": 50,
        "program_budget": 310000000,
        "project_budget": "from 20 t. to 50 t. EUR",
        "type": "collectibe",
        "is_scientific_degree_required": true,
        "minimal_scientist_experience": "less than 1 year",
        "link": "https://content.iospress.com/articles/journal-of-intelligent-and-fuzzy-systems/ifs169843"
    },
    {
        "title": "Machine learning 1",
        "purpose": "One who may seem plain at first in appearance or capability, but later turns out to be beautiful or great.",
        "documents_submission_date_start": "2019-01-12",
        "documents_submission_date_end": "2019-01-15",
        "documents_submission_time_end": "14:21",
        "is_urgent": false,
        "competition_results_date": "2019-02-01",
        "fund_name": "NAWA",
        "country": "China",
        "allowed_participant_countries": "Canada",
        "id": "231sfds",
        "field_of_knoweledge": "Machine Learning",
        "specific_objectives": "researching of machine learnign technology",
        "expected_impact": "short term",
        "description": "this grant is very important for our society. It brings new ideas to the Programming world.",
        "allowed_participants": "small bussiness, academy",
        "allowed_participants_age": 50,
        "program_budget": 310000000,
        "project_budget": "from 20 t. to 50 t. EUR",
        "type": "collectibe",
        "is_scientific_degree_required": true,
        "minimal_scientist_experience": "less than 1 year",
        "link": "https://content.iospress.com/articles/journal-of-intelligent-and-fuzzy-systems/ifs169843"
    },
    {
        "title": "Sociology",
        "purpose": "One who may seem plain at first in appearance or capability, but later turns out to be beautiful or great.",
        "documents_submission_date_start": "2019-01-12",
        "documents_submission_date_end": "2019-01-15",
        "documents_submission_time_end": "14:21",
        "is_urgent": false,
        "competition_results_date": "2019-02-01",
        "fund_name": "NAWA",
        "country": "China",
        "allowed_participant_countries": "Canada",
        "id": "231sfds",
        "field_of_knoweledge": "Sociology",
        "specific_objectives": "researching sociology fields",
        "expected_impact": "short term",
        "description": "this grant is very important for our society. It brings new ideas to the Society world.",
        "allowed_participants": "small bussiness, academy",
        "allowed_participants_age": 50,
        "program_budget": 310000000,
        "project_budget": "from 20 t. to 50 t. EUR",
        "type": "collectibe",
        "is_scientific_degree_required": true,
        "minimal_scientist_experience": "less than 1 year",
        "link": "https://content.iospress.com/articles/journal-of-intelligent-and-fuzzy-systems/ifs169843"
    },
    {
        "title": "Geodezy",
        "purpose": "One who may seem plain at first in appearance or capability, but later turns out to be beautiful or great.",
        "documents_submission_date_start": "2019-01-12",
        "documents_submission_date_end": "2019-01-15",
        "documents_submission_time_end": "14:21",
        "is_urgent": false,
        "competition_results_date": "2019-02-01",
        "fund_name": "NAWA",
        "country": "USA",
        "allowed_participant_countries": "Canada",
        "id": "231sfds",
        "field_of_knoweledge": "Geodezy",
        "specific_objectives": "Geodezy",
        "expected_impact": "short term",
        "description": "geodezy is very impoernat part of our lives",
        "allowed_participants": "small bussiness, academy",
        "allowed_participants_age": 50,
        "program_budget": 310000000,
        "project_budget": "from 20 t. to 50 t. EUR",
        "type": "collectibe",
        "is_scientific_degree_required": true,
        "minimal_scientist_experience": "less than 1 year",
        "link": "https://content.iospress.com/articles/journal-of-intelligent-and-fuzzy-systems/ifs169843"
    },
    {
        "title": "Architecture",
        "purpose": "One who may seem plain at first in appearance or capability, but later turns out to be beautiful or great.",
        "documents_submission_date_start": "2019-01-12",
        "documents_submission_date_end": "2019-01-15",
        "documents_submission_time_end": "14:21",
        "is_urgent": false,
        "competition_results_date": "2019-02-01",
        "fund_name": "NAWA",
        "country": "USA",
        "allowed_participant_countries": "Canada",
        "id": "231sfds",
        "field_of_knoweledge": "Architecture",
        "specific_objectives": "Architecture priorities",
        "expected_impact": "short term",
        "description": "geodezy is very impoernat part of our lives",
        "allowed_participants": "small bussiness, academy",
        "allowed_participants_age": 50,
        "program_budget": 310000000,
        "project_budget": "from 20 t. to 50 t. EUR",
        "type": "collectibe",
        "is_scientific_degree_required": true,
        "minimal_scientist_experience": "less than 1 year",
        "link": "https://content.iospress.com/articles/journal-of-intelligent-and-fuzzy-systems/ifs169843"
    }
    {
        "title": "Filming",
        "purpose": "One who may seem plain at first in appearance or capability, but later turns out to be beautiful or great.",
        "documents_submission_date_start": "2019-01-12",
        "documents_submission_date_end": "2019-01-15",
        "documents_submission_time_end": "14:21",
        "is_urgent": false,
        "competition_results_date": "2019-02-01",
        "fund_name": "NAWA",
        "country": "USA",
        "allowed_participant_countries": "Canada",
        "id": "231sfds",
        "field_of_knoweledge": "Filming",
        "specific_objectives": "Filming priorities",
        "expected_impact": "short term",
        "description": "geodezy is very impoernat part of our lives",
        "allowed_participants": "small bussiness, academy",
        "allowed_participants_age": 50,
        "program_budget": 310000000,
        "project_budget": "from 20 t. to 50 t. EUR",
        "type": "collectibe",
        "is_scientific_degree_required": true,
        "minimal_scientist_experience": "less than 1 year",
        "link": "https://content.iospress.com/articles/journal-of-intelligent-and-fuzzy-systems/ifs169843"
    }
]